hbookerAPI/__init__.py
hbookerAPI/hbookerAPI.py
hbookerAPI-0.1.dist-info/LICENSE.md
hbookerAPI-0.1.dist-info/METADATA
hbookerAPI-0.1.dist-info/WHEEL
hbookerAPI-0.1.dist-info/top_level.txt
hbookerAPI-0.1.dist-info/RECORD
