Metadata-Version: 2.1
Name: hbookerAPI
Version: 0.1
Summary: 刺猬猫/欢乐书客客户端API实现.
Home-page: https://github.com/abc55660745/hbookerAPI
Author: bismarck
Author-email: wsgrbsm@gmail.com
License: MIT
Keywords: hbooker,ciweimao
Platform: UNKNOWN
Requires-Python: >=3.4.0
Requires-Dist: setuptools
Requires-Dist: ujson
Requires-Dist: requests
Requires-Dist: pandas
Requires-Dist: pycryptodome
